cmip_ref_metrics_pmp/__init__.py
cmip_ref_metrics_pmp/annual_cycle.py
cmip_ref_metrics_pmp/pmp_driver.py
cmip_ref_metrics_pmp/py.typed
cmip_ref_metrics_pmp/variability_modes.py
cmip_ref_metrics_pmp/dataset_registry/pmp_climatology.txt
cmip_ref_metrics_pmp/params/pmp_param_MoV-psl.py
cmip_ref_metrics_pmp/params/pmp_param_MoV-ts.py
cmip_ref_metrics_pmp/params/pmp_param_annualcycle_1-clims.py
cmip_ref_metrics_pmp/params/pmp_param_annualcycle_2-metrics.py
cmip_ref_metrics_pmp/requirements/conda-lock.yml
cmip_ref_metrics_pmp/requirements/environment.yml
cmip_ref_metrics_pmp-0.4.1.dist-info/METADATA
cmip_ref_metrics_pmp-0.4.1.dist-info/WHEEL
cmip_ref_metrics_pmp-0.4.1.dist-info/licenses/LICENCE
cmip_ref_metrics_pmp-0.4.1.dist-info/licenses/NOTICE
cmip_ref_metrics_pmp-0.4.1.dist-info/RECORD
